docs/conf.py
openghg_inversions/__init__.py
openghg_inversions/array_ops.py
openghg_inversions/convert.py
openghg_inversions/filters.py
openghg_inversions/model_error.py
openghg_inversions/utils.py
openghg_inversions/basis/__init__.py
openghg_inversions/basis/_functions.py
openghg_inversions/basis/_helpers.py
openghg_inversions/basis/_wrapper.py
openghg_inversions/basis/outer_region_definition_EASTASIA.nc
openghg_inversions/basis/outer_region_definition_EUROPE.nc
openghg_inversions/basis/algorithms/__init__.py
openghg_inversions/basis/algorithms/_quadtree.py
openghg_inversions/basis/algorithms/_weighted.py
openghg_inversions/basis/algorithms/country-EUROPE-UKMO-landsea-2023.nc
openghg_inversions/basis/algorithms/country-land-sea_EASTASIA.nc
openghg_inversions/config/__init__.py
openghg_inversions/config/config.py
openghg_inversions/config/paths.py
openghg_inversions/config/version.py
openghg_inversions/hbmcmc/__init__.py
openghg_inversions/hbmcmc/components.py
openghg_inversions/hbmcmc/hbmcmc.py
openghg_inversions/hbmcmc/hbmcmc_output.py
openghg_inversions/hbmcmc/hbmcmc_post_process.py
openghg_inversions/hbmcmc/inversion_pymc.py
openghg_inversions/hbmcmc/inversionsetup.py
openghg_inversions/hbmcmc/post_process_inputs.py
openghg_inversions/hbmcmc/run_hbmcmc.py
openghg_inversions/hbmcmc/config/openghg_hbmcmc_input_satellite_template.ini
openghg_inversions/hbmcmc/config/openghg_hbmcmc_input_template.ini
openghg_inversions/hbmcmc/config/openghg_hbmcmc_input_template_example.ini
openghg_inversions/inversion_data/__init__.py
openghg_inversions/inversion_data/get_data.py
openghg_inversions/inversion_data/getters.py
openghg_inversions/inversion_data/scenario.py
openghg_inversions/inversion_data/serialise.py
openghg_inversions/postprocessing/PARIS_Lagrangian_inversion_concentration_EUROPE_v03.cdl
openghg_inversions/postprocessing/PARIS_Lagrangian_inversion_flux_EUROPE.cdl
openghg_inversions/postprocessing/__init__.py
openghg_inversions/postprocessing/_country_codes.py
openghg_inversions-0.6.0.dist-info/licenses/LICENSE
openghg_inversions-0.6.0.dist-info/METADATA
openghg_inversions-0.6.0.dist-info/WHEEL
openghg_inversions-0.6.0.dist-info/top_level.txt
openghg_inversions-0.6.0.dist-info/RECORD
