Metadata-Version: 2.4
Name: openghg_inversions
Version: 0.6.0
Summary: OpenGHG Inversions
Author-email: Eric Saboya <eric.saboya@bristol.ac.uk>
Maintainer-email: Brendan Murphy <brendan.murphy@bristol.ac.uk>
License: MIT License
Project-URL: Home, https://github.com/openghg/openghg_inversions
Project-URL: Bug Tracker, https://github.com/openghg/openghg_inversions/issues
Classifier: Programming Language :: Python :: 3
Classifier: License :: OSI Approved :: MIT License
Classifier: Operating System :: OS Independent
Requires-Python: >=3.10
License-File: LICENSE
Requires-Dist: numpy>=2.0
Requires-Dist: numba>=0.59
Requires-Dist: pymc
Requires-Dist: numpyro[cpu]
Requires-Dist: xarray>=2025.06.0
Requires-Dist: pandas
Requires-Dist: matplotlib
Requires-Dist: scipy
Requires-Dist: numpy
Requires-Dist: openghg
Requires-Dist: sparse
Requires-Dist: flox
Requires-Dist: opt_einsum
Dynamic: license-file
